lyz_test_py_pypi/__init__.py
lyz_test_py_pypi/client.py
lyz_test_py_pypi-0.0.1.dist-info/licenses/LICENSE
lyz_test_py_pypi-0.0.1.dist-info/METADATA
lyz_test_py_pypi-0.0.1.dist-info/WHEEL
lyz_test_py_pypi-0.0.1.dist-info/top_level.txt
lyz_test_py_pypi-0.0.1.dist-info/RECORD
