Metadata-Version: 2.4
Name: lyz_test_py_pypi
Version: 0.0.1
Summary: This is a test sdk.
Author-email: seven <sevenluo1999@gmail.com>
Project-URL: Homepage, https://github.com/longaosky/test-py-pypi
Project-URL: Repository, https://github.com/longaosky/test-py-pypi
Requires-Python: >=3.8
License-File: LICENSE
Dynamic: license-file
